{
  "generated_at": "2026-07-01T03:27:44.037081+00:00",
  "coarse": null,
  "fine": [
    {
      "half_life_days": 30,
      "overall": {
        "brier_score": 0.5884803381079086,
        "log_loss": 0.975843415178839,
        "direction_accuracy": 0.5344827586206896,
        "direction_counts": {
          "correct": 31,
          "wrong": 27
        }
      },
      "n_matches_evaluated": 58,
      "walk_forward_fits": 17,
      "fit_time_s": 695.3,
      "details": [
        {
          "match": "Mexico vs South Africa",
          "date": "2026-06-11",
          "stage": "Group A - Matchday 1",
          "actual": "2-0",
          "pred_home": 0.4216,
          "pred_draw": 0.5292,
          "pred_away": 0.0492,
          "brier": 0.61708,
          "direction": "wrong"
        },
        {
          "match": "South Korea vs Czech Republic",
          "date": "2026-06-12",
          "stage": "Group A - Matchday 1",
          "actual": "2-1",
          "pred_home": 0.5151,
          "pred_draw": 0.2443,
          "pred_away": 0.2406,
          "brier": 0.35271,
          "direction": "correct"
        },
        {
          "match": "Canada vs Bosnia and Herzegovina",
          "date": "2026-06-12",
          "stage": "Group B - Matchday 1",
          "actual": "1-1",
          "pred_home": 0.302,
          "pred_draw": 0.4062,
          "pred_away": 0.2918,
          "brier": 0.529,
          "direction": "correct"
        },
        {
          "match": "United States vs Paraguay",
          "date": "2026-06-13",
          "stage": "Group D - Matchday 1",
          "actual": "4-1",
          "pred_home": 0.3001,
          "pred_draw": 0.2721,
          "pred_away": 0.4277,
          "brier": 0.74682,
          "direction": "wrong"
        },
        {
          "match": "Australia vs Turkey",
          "date": "2026-06-13",
          "stage": "Group D - Matchday 1",
          "actual": "2-0",
          "pred_home": 0.2466,
          "pred_draw": 0.4807,
          "pred_away": 0.2726,
          "brier": 0.87297,
          "direction": "wrong"
        },
        {
          "match": "Qatar vs Switzerland",
          "date": "2026-06-13",
          "stage": "Group B - Matchday 1",
          "actual": "1-1",
          "pred_home": 0.1139,
          "pred_draw": 0.301,
          "pred_away": 0.585,
          "brier": 0.84383,
          "direction": "wrong"
        },
        {
          "match": "Brazil vs Morocco",
          "date": "2026-06-13",
          "stage": "Group C - Matchday 1",
          "actual": "1-1",
          "pred_home": 0.0905,
          "pred_draw": 0.1563,
          "pred_away": 0.7532,
          "brier": 1.28742,
          "direction": "wrong"
        },
        {
          "match": "Haiti vs Scotland",
          "date": "2026-06-14",
          "stage": "Group C - Matchday 1",
          "actual": "0-1",
          "pred_home": 0.1829,
          "pred_draw": 0.3191,
          "pred_away": 0.4979,
          "brier": 0.38739,
          "direction": "correct"
        },
        {
          "match": "Germany vs Curacao",
          "date": "2026-06-14",
          "stage": "Group E - Matchday 1",
          "actual": "7-1",
          "pred_home": 0.9699,
          "pred_draw": 0.0238,
          "pred_away": 0.0063,
          "brier": 0.00151,
          "direction": "correct"
        },
        {
          "match": "Netherlands vs Japan",
          "date": "2026-06-14",
          "stage": "Group F - Matchday 1",
          "actual": "2-2",
          "pred_home": 0.167,
          "pred_draw": 0.4434,
          "pred_away": 0.3897,
          "brier": 0.48956,
          "direction": "correct"
        },
        {
          "match": "Ivory Coast vs Ecuador",
          "date": "2026-06-14",
          "stage": "Group E - Matchday 1",
          "actual": "1-0",
          "pred_home": 0.4463,
          "pred_draw": 0.3395,
          "pred_away": 0.2142,
          "brier": 0.4677,
          "direction": "correct"
        },
        {
          "match": "Tunisia vs Sweden",
          "date": "2026-06-15",
          "stage": "Group F - Matchday 1",
          "actual": "1-5",
          "pred_home": 0.2945,
          "pred_draw": 0.3432,
          "pred_away": 0.3623,
          "brier": 0.61108,
          "direction": "correct"
        },
        {
          "match": "Spain vs Cape Verde",
          "date": "2026-06-15",
          "stage": "Group H - Matchday 1",
          "actual": "0-0",
          "pred_home": 0.2576,
          "pred_draw": 0.3522,
          "pred_away": 0.3903,
          "brier": 0.63836,
          "direction": "wrong"
        },
        {
          "match": "Belgium vs Egypt",
          "date": "2026-06-15",
          "stage": "Group G - Matchday 1",
          "actual": "1-1",
          "pred_home": 0.3887,
          "pred_draw": 0.3804,
          "pred_away": 0.2309,
          "brier": 0.58828,
          "direction": "wrong"
        },
        {
          "match": "Saudi Arabia vs Uruguay",
          "date": "2026-06-15",
          "stage": "Group H - Matchday 1",
          "actual": "1-1",
          "pred_home": 0.1665,
          "pred_draw": 0.309,
          "pred_away": 0.5244,
          "brier": 0.78019,
          "direction": "wrong"
        },
        {
          "match": "Iran vs New Zealand",
          "date": "2026-06-16",
          "stage": "Group G - Matchday 1",
          "actual": "2-2",
          "pred_home": 0.5224,
          "pred_draw": 0.2786,
          "pred_away": 0.199,
          "brier": 0.83303,
          "direction": "wrong"
        },
        {
          "match": "France vs Senegal",
          "date": "2026-06-16",
          "stage": "Group I - Matchday 1",
          "actual": "3-1",
          "pred_home": 0.3444,
          "pred_draw": 0.3094,
          "pred_away": 0.3462,
          "brier": 0.64533,
          "direction": "wrong"
        },
        {
          "match": "Iraq vs Norway",
          "date": "2026-06-16",
          "stage": "Group I - Matchday 1",
          "actual": "1-4",
          "pred_home": 0.3985,
          "pred_draw": 0.3906,
          "pred_away": 0.2109,
          "brier": 0.93394,
          "direction": "wrong"
        },
        {
          "match": "Argentina vs Algeria",
          "date": "2026-06-17",
          "stage": "Group J - Matchday 1",
          "actual": "3-0",
          "pred_home": 0.2974,
          "pred_draw": 0.3503,
          "pred_away": 0.3523,
          "brier": 0.74053,
          "direction": "wrong"
        },
        {
          "match": "Austria vs Jordan",
          "date": "2026-06-17",
          "stage": "Group J - Matchday 1",
          "actual": "3-1",
          "pred_home": 0.5944,
          "pred_draw": 0.2564,
          "pred_away": 0.1492,
          "brier": 0.25245,
          "direction": "correct"
        },
        {
          "match": "Portugal vs DR Congo",
          "date": "2026-06-17",
          "stage": "Group K - Matchday 1",
          "actual": "1-1",
          "pred_home": 0.2898,
          "pred_draw": 0.4208,
          "pred_away": 0.2895,
          "brier": 0.50328,
          "direction": "correct"
        },
        {
          "match": "England vs Croatia",
          "date": "2026-06-17",
          "stage": "Group L - Matchday 1",
          "actual": "4-2",
          "pred_home": 0.3856,
          "pred_draw": 0.381,
          "pred_away": 0.2334,
          "brier": 0.5772,
          "direction": "correct"
        },
        {
          "match": "Ghana vs Panama",
          "date": "2026-06-17",
          "stage": "Group L - Matchday 1",
          "actual": "1-0",
          "pred_home": 0.4142,
          "pred_draw": 0.2753,
          "pred_away": 0.3105,
          "brier": 0.51535,
          "direction": "correct"
        },
        {
          "match": "Uzbekistan vs Colombia",
          "date": "2026-06-18",
          "stage": "Group K - Matchday 1",
          "actual": "1-3",
          "pred_home": 0.3837,
          "pred_draw": 0.3612,
          "pred_away": 0.2551,
          "brier": 0.83247,
          "direction": "wrong"
        },
        {
          "match": "Czech Republic vs South Africa",
          "date": "2026-06-18",
          "stage": "Group A - Matchday 2",
          "actual": "1-1",
          "pred_home": 0.5552,
          "pred_draw": 0.2997,
          "pred_away": 0.1451,
          "brier": 0.81977,
          "direction": "wrong"
        },
        {
          "match": "Switzerland vs Bosnia and Herzegovina",
          "date": "2026-06-18",
          "stage": "Group B - Matchday 2",
          "actual": "4-1",
          "pred_home": 0.4134,
          "pred_draw": 0.3499,
          "pred_away": 0.2367,
          "brier": 0.52262,
          "direction": "correct"
        },
        {
          "match": "Canada vs Qatar",
          "date": "2026-06-18",
          "stage": "Group B - Matchday 2",
          "actual": "6-0",
          "pred_home": 0.2764,
          "pred_draw": 0.4016,
          "pred_away": 0.322,
          "brier": 0.78859,
          "direction": "wrong"
        },
        {
          "match": "Mexico vs South Korea",
          "date": "2026-06-19",
          "stage": "Group A - Matchday 2",
          "actual": "1-0",
          "pred_home": 0.4487,
          "pred_draw": 0.3521,
          "pred_away": 0.1992,
          "brier": 0.46753,
          "direction": "correct"
        },
        {
          "match": "United States vs Australia",
          "date": "2026-06-19",
          "stage": "Group D - Matchday 2",
          "actual": "2-0",
          "pred_home": 0.2275,
          "pred_draw": 0.271,
          "pred_away": 0.5016,
          "brier": 0.92183,
          "direction": "wrong"
        },
        {
          "match": "Scotland vs Morocco",
          "date": "2026-06-19",
          "stage": "Group C - Matchday 2",
          "actual": "0-1",
          "pred_home": 0.2696,
          "pred_draw": 0.4145,
          "pred_away": 0.316,
          "brier": 0.71235,
          "direction": "wrong"
        },
        {
          "match": "Brazil vs Haiti",
          "date": "2026-06-20",
          "stage": "Group C - Matchday 2",
          "actual": "3-0",
          "pred_home": 0.6674,
          "pred_draw": 0.2413,
          "pred_away": 0.0913,
          "brier": 0.17719,
          "direction": "correct"
        },
        {
          "match": "Turkey vs Paraguay",
          "date": "2026-06-20",
          "stage": "Group D - Matchday 2",
          "actual": "0-1",
          "pred_home": 0.3472,
          "pred_draw": 0.3203,
          "pred_away": 0.3325,
          "brier": 0.6686,
          "direction": "wrong"
        },
        {
          "match": "Netherlands vs Sweden",
          "date": "2026-06-20",
          "stage": "Group F - Matchday 2",
          "actual": "5-1",
          "pred_home": 0.1483,
          "pred_draw": 0.1777,
          "pred_away": 0.674,
          "brier": 1.21126,
          "direction": "wrong"
        },
        {
          "match": "Germany vs Ivory Coast",
          "date": "2026-06-20",
          "stage": "Group E - Matchday 2",
          "actual": "2-1",
          "pred_home": 0.4658,
          "pred_draw": 0.3128,
          "pred_away": 0.2214,
          "brier": 0.43227,
          "direction": "correct"
        },
        {
          "match": "Ecuador vs Curacao",
          "date": "2026-06-21",
          "stage": "Group E - Matchday 2",
          "actual": "0-0",
          "pred_home": 0.5834,
          "pred_draw": 0.2656,
          "pred_away": 0.1509,
          "brier": 0.90249,
          "direction": "wrong"
        },
        {
          "match": "Tunisia vs Japan",
          "date": "2026-06-21",
          "stage": "Group F - Matchday 2",
          "actual": "0-4",
          "pred_home": 0.0509,
          "pred_draw": 0.1401,
          "pred_away": 0.809,
          "brier": 0.05868,
          "direction": "correct"
        },
        {
          "match": "Spain vs Saudi Arabia",
          "date": "2026-06-21",
          "stage": "Group H - Matchday 2",
          "actual": "4-0",
          "pred_home": 0.3855,
          "pred_draw": 0.4326,
          "pred_away": 0.1819,
          "brier": 0.59785,
          "direction": "wrong"
        },
        {
          "match": "Belgium vs Iran",
          "date": "2026-06-21",
          "stage": "Group G - Matchday 2",
          "actual": "2-1",
          "pred_home": 0.4374,
          "pred_draw": 0.2722,
          "pred_away": 0.2904,
          "brier": 0.47493,
          "direction": "correct"
        },
        {
          "match": "Uruguay vs Cape Verde",
          "date": "2026-06-21",
          "stage": "Group H - Matchday 2",
          "actual": "2-2",
          "pred_home": 0.1907,
          "pred_draw": 0.4428,
          "pred_away": 0.3665,
          "brier": 0.48118,
          "direction": "correct"
        },
        {
          "match": "New Zealand vs Egypt",
          "date": "2026-06-22",
          "stage": "Group G - Matchday 2",
          "actual": "1-3",
          "pred_home": 0.141,
          "pred_draw": 0.3186,
          "pred_away": 0.5403,
          "brier": 0.3327,
          "direction": "correct"
        },
        {
          "match": "Argentina vs Austria",
          "date": "2026-06-22",
          "stage": "Group J - Matchday 2",
          "actual": "2-0",
          "pred_home": 0.6788,
          "pred_draw": 0.2239,
          "pred_away": 0.0973,
          "brier": 0.16278,
          "direction": "correct"
        },
        {
          "match": "France vs Iraq",
          "date": "2026-06-22",
          "stage": "Group I - Matchday 2",
          "actual": "3-0",
          "pred_home": 0.892,
          "pred_draw": 0.0783,
          "pred_away": 0.0296,
          "brier": 0.01867,
          "direction": "correct"
        },
        {
          "match": "Norway vs Senegal",
          "date": "2026-06-23",
          "stage": "Group I - Matchday 2",
          "actual": "3-2",
          "pred_home": 0.679,
          "pred_draw": 0.1891,
          "pred_away": 0.1319,
          "brier": 0.15621,
          "direction": "correct"
        },
        {
          "match": "Jordan vs Algeria",
          "date": "2026-06-23",
          "stage": "Group J - Matchday 2",
          "actual": "1-2",
          "pred_home": 0.3648,
          "pred_draw": 0.2948,
          "pred_away": 0.3404,
          "brier": 0.655,
          "direction": "wrong"
        },
        {
          "match": "Portugal vs Uzbekistan",
          "date": "2026-06-23",
          "stage": "Group K - Matchday 2",
          "actual": "5-0",
          "pred_home": 0.548,
          "pred_draw": 0.2917,
          "pred_away": 0.1603,
          "brier": 0.31509,
          "direction": "correct"
        },
        {
          "match": "England vs Ghana",
          "date": "2026-06-23",
          "stage": "Group L - Matchday 2",
          "actual": "0-0",
          "pred_home": 0.4194,
          "pred_draw": 0.3249,
          "pred_away": 0.2558,
          "brier": 0.69705,
          "direction": "wrong"
        },
        {
          "match": "Panama vs Croatia",
          "date": "2026-06-23",
          "stage": "Group L - Matchday 2",
          "actual": "0-1",
          "pred_home": 0.2456,
          "pred_draw": 0.2708,
          "pred_away": 0.4836,
          "brier": 0.40033,
          "direction": "correct"
        },
        {
          "match": "Colombia vs DR Congo",
          "date": "2026-06-24",
          "stage": "Group K - Matchday 2",
          "actual": "1-0",
          "pred_home": 0.3958,
          "pred_draw": 0.337,
          "pred_away": 0.2671,
          "brier": 0.54999,
          "direction": "correct"
        },
        {
          "match": "Switzerland vs Canada",
          "date": "2026-06-24",
          "stage": "Group B - Matchday 3",
          "actual": "2-1",
          "pred_home": 0.1895,
          "pred_draw": 0.2654,
          "pred_away": 0.5451,
          "brier": 1.02445,
          "direction": "wrong"
        },
        {
          "match": "Bosnia and Herzegovina vs Qatar",
          "date": "2026-06-24",
          "stage": "Group B - Matchday 3",
          "actual": "3-1",
          "pred_home": 0.4972,
          "pred_draw": 0.3065,
          "pred_away": 0.1963,
          "brier": 0.38532,
          "direction": "correct"
        },
        {
          "match": "Scotland vs Brazil",
          "date": "2026-06-24",
          "stage": "Group C - Matchday 3",
          "actual": "0-3",
          "pred_home": 0.1474,
          "pred_draw": 0.352,
          "pred_away": 0.5006,
          "brier": 0.39503,
          "direction": "correct"
        },
        {
          "match": "Morocco vs Haiti",
          "date": "2026-06-24",
          "stage": "Group C - Matchday 3",
          "actual": "4-2",
          "pred_home": 0.8512,
          "pred_draw": 0.1332,
          "pred_away": 0.0156,
          "brier": 0.04011,
          "direction": "correct"
        },
        {
          "match": "Czech Republic vs Mexico",
          "date": "2026-06-25",
          "stage": "Group A - Matchday 3",
          "actual": "0-3",
          "pred_home": 0.0413,
          "pred_draw": 0.1872,
          "pred_away": 0.7714,
          "brier": 0.08901,
          "direction": "correct"
        },
        {
          "match": "South Africa vs South Korea",
          "date": "2026-06-25",
          "stage": "Group A - Matchday 3",
          "actual": "1-0",
          "pred_home": 0.09,
          "pred_draw": 0.3017,
          "pred_away": 0.6084,
          "brier": 1.28921,
          "direction": "wrong"
        },
        {
          "match": "South Africa vs Canada",
          "date": "2026-06-28",
          "stage": "Round of 32",
          "actual": "0-1",
          "pred_home": 0.1148,
          "pred_draw": 0.3096,
          "pred_away": 0.5756,
          "brier": 0.28919,
          "direction": "correct"
        },
        {
          "match": "Netherlands vs Morocco",
          "date": "2026-06-29",
          "stage": "Round of 32",
          "actual": "1-1",
          "pred_home": 0.5259,
          "pred_draw": 0.2347,
          "pred_away": 0.2394,
          "brier": 0.91954,
          "direction": "wrong"
        },
        {
          "match": "Germany vs Paraguay",
          "date": "2026-06-29",
          "stage": "Round of 32",
          "actual": "1-1",
          "pred_home": 0.8667,
          "pred_draw": 0.0937,
          "pred_away": 0.0396,
          "brier": 1.57405,
          "direction": "wrong"
        },
        {
          "match": "Brazil vs Japan",
          "date": "2026-06-29",
          "stage": "Round of 32 - 1st Group C vs 2nd Group F",
          "actual": "2-1",
          "pred_home": 0.3938,
          "pred_draw": 0.3376,
          "pred_away": 0.2685,
          "brier": 0.55353,
          "direction": "correct"
        }
      ]
    },
    {
      "half_life_days": 60,
      "overall": {
        "brier_score": 0.5541272941633949,
        "log_loss": 0.9283869880429173,
        "direction_accuracy": 0.5517241379310345,
        "direction_counts": {
          "correct": 32,
          "wrong": 26
        }
      },
      "n_matches_evaluated": 58,
      "walk_forward_fits": 17,
      "fit_time_s": 723.2,
      "details": [
        {
          "match": "Mexico vs South Africa",
          "date": "2026-06-11",
          "stage": "Group A - Matchday 1",
          "actual": "2-0",
          "pred_home": 0.771,
          "pred_draw": 0.1943,
          "pred_away": 0.0347,
          "brier": 0.09137,
          "direction": "correct"
        },
        {
          "match": "South Korea vs Czech Republic",
          "date": "2026-06-12",
          "stage": "Group A - Matchday 1",
          "actual": "2-1",
          "pred_home": 0.3221,
          "pred_draw": 0.3319,
          "pred_away": 0.3461,
          "brier": 0.68951,
          "direction": "wrong"
        },
        {
          "match": "Canada vs Bosnia and Herzegovina",
          "date": "2026-06-12",
          "stage": "Group B - Matchday 1",
          "actual": "1-1",
          "pred_home": 0.2464,
          "pred_draw": 0.4662,
          "pred_away": 0.2874,
          "brier": 0.42828,
          "direction": "correct"
        },
        {
          "match": "United States vs Paraguay",
          "date": "2026-06-13",
          "stage": "Group D - Matchday 1",
          "actual": "4-1",
          "pred_home": 0.3988,
          "pred_draw": 0.3063,
          "pred_away": 0.2949,
          "brier": 0.54219,
          "direction": "correct"
        },
        {
          "match": "Australia vs Turkey",
          "date": "2026-06-13",
          "stage": "Group D - Matchday 1",
          "actual": "2-0",
          "pred_home": 0.3453,
          "pred_draw": 0.3093,
          "pred_away": 0.3453,
          "brier": 0.64354,
          "direction": "correct"
        },
        {
          "match": "Qatar vs Switzerland",
          "date": "2026-06-13",
          "stage": "Group B - Matchday 1",
          "actual": "1-1",
          "pred_home": 0.2949,
          "pred_draw": 0.3063,
          "pred_away": 0.3988,
          "brier": 0.72722,
          "direction": "wrong"
        },
        {
          "match": "Brazil vs Morocco",
          "date": "2026-06-13",
          "stage": "Group C - Matchday 1",
          "actual": "1-1",
          "pred_home": 0.3981,
          "pred_draw": 0.3081,
          "pred_away": 0.2937,
          "brier": 0.72346,
          "direction": "wrong"
        },
        {
          "match": "Haiti vs Scotland",
          "date": "2026-06-14",
          "stage": "Group C - Matchday 1",
          "actual": "0-1",
          "pred_home": 0.1614,
          "pred_draw": 0.3434,
          "pred_away": 0.4953,
          "brier": 0.3987,
          "direction": "correct"
        },
        {
          "match": "Germany vs Curacao",
          "date": "2026-06-14",
          "stage": "Group E - Matchday 1",
          "actual": "7-1",
          "pred_home": 0.9502,
          "pred_draw": 0.0387,
          "pred_away": 0.011,
          "brier": 0.0041,
          "direction": "correct"
        },
        {
          "match": "Netherlands vs Japan",
          "date": "2026-06-14",
          "stage": "Group F - Matchday 1",
          "actual": "2-2",
          "pred_home": 0.2314,
          "pred_draw": 0.4621,
          "pred_away": 0.3064,
          "brier": 0.43678,
          "direction": "correct"
        },
        {
          "match": "Ivory Coast vs Ecuador",
          "date": "2026-06-14",
          "stage": "Group E - Matchday 1",
          "actual": "1-0",
          "pred_home": 0.552,
          "pred_draw": 0.324,
          "pred_away": 0.124,
          "brier": 0.32108,
          "direction": "correct"
        },
        {
          "match": "Tunisia vs Sweden",
          "date": "2026-06-15",
          "stage": "Group F - Matchday 1",
          "actual": "1-5",
          "pred_home": 0.5656,
          "pred_draw": 0.2469,
          "pred_away": 0.1876,
          "brier": 1.04084,
          "direction": "wrong"
        },
        {
          "match": "Spain vs Cape Verde",
          "date": "2026-06-15",
          "stage": "Group H - Matchday 1",
          "actual": "0-0",
          "pred_home": 0.5783,
          "pred_draw": 0.2832,
          "pred_away": 0.1386,
          "brier": 0.8674,
          "direction": "wrong"
        },
        {
          "match": "Belgium vs Egypt",
          "date": "2026-06-15",
          "stage": "Group G - Matchday 1",
          "actual": "1-1",
          "pred_home": 0.4091,
          "pred_draw": 0.3813,
          "pred_away": 0.2096,
          "brier": 0.59409,
          "direction": "wrong"
        },
        {
          "match": "Saudi Arabia vs Uruguay",
          "date": "2026-06-15",
          "stage": "Group H - Matchday 1",
          "actual": "1-1",
          "pred_home": 0.1029,
          "pred_draw": 0.3202,
          "pred_away": 0.5769,
          "brier": 0.80563,
          "direction": "wrong"
        },
        {
          "match": "Iran vs New Zealand",
          "date": "2026-06-16",
          "stage": "Group G - Matchday 1",
          "actual": "2-2",
          "pred_home": 0.7079,
          "pred_draw": 0.2047,
          "pred_away": 0.0874,
          "brier": 1.14118,
          "direction": "wrong"
        },
        {
          "match": "France vs Senegal",
          "date": "2026-06-16",
          "stage": "Group I - Matchday 1",
          "actual": "3-1",
          "pred_home": 0.5843,
          "pred_draw": 0.2467,
          "pred_away": 0.169,
          "brier": 0.26219,
          "direction": "correct"
        },
        {
          "match": "Iraq vs Norway",
          "date": "2026-06-16",
          "stage": "Group I - Matchday 1",
          "actual": "1-4",
          "pred_home": 0.2459,
          "pred_draw": 0.4274,
          "pred_away": 0.3268,
          "brier": 0.69628,
          "direction": "wrong"
        },
        {
          "match": "Argentina vs Algeria",
          "date": "2026-06-17",
          "stage": "Group J - Matchday 1",
          "actual": "3-0",
          "pred_home": 0.2436,
          "pred_draw": 0.3206,
          "pred_away": 0.4358,
          "brier": 0.86478,
          "direction": "wrong"
        },
        {
          "match": "Austria vs Jordan",
          "date": "2026-06-17",
          "stage": "Group J - Matchday 1",
          "actual": "3-1",
          "pred_home": 0.7177,
          "pred_draw": 0.1863,
          "pred_away": 0.0961,
          "brier": 0.12363,
          "direction": "correct"
        },
        {
          "match": "Portugal vs DR Congo",
          "date": "2026-06-17",
          "stage": "Group K - Matchday 1",
          "actual": "1-1",
          "pred_home": 0.2682,
          "pred_draw": 0.4544,
          "pred_away": 0.2774,
          "brier": 0.44664,
          "direction": "correct"
        },
        {
          "match": "England vs Croatia",
          "date": "2026-06-17",
          "stage": "Group L - Matchday 1",
          "actual": "4-2",
          "pred_home": 0.36,
          "pred_draw": 0.3781,
          "pred_away": 0.2618,
          "brier": 0.62108,
          "direction": "wrong"
        },
        {
          "match": "Ghana vs Panama",
          "date": "2026-06-17",
          "stage": "Group L - Matchday 1",
          "actual": "1-0",
          "pred_home": 0.2982,
          "pred_draw": 0.2747,
          "pred_away": 0.4272,
          "brier": 0.75047,
          "direction": "wrong"
        },
        {
          "match": "Uzbekistan vs Colombia",
          "date": "2026-06-18",
          "stage": "Group K - Matchday 1",
          "actual": "1-3",
          "pred_home": 0.2473,
          "pred_draw": 0.2992,
          "pred_away": 0.4535,
          "brier": 0.44928,
          "direction": "correct"
        },
        {
          "match": "Czech Republic vs South Africa",
          "date": "2026-06-18",
          "stage": "Group A - Matchday 2",
          "actual": "1-1",
          "pred_home": 0.3719,
          "pred_draw": 0.3083,
          "pred_away": 0.3198,
          "brier": 0.71894,
          "direction": "wrong"
        },
        {
          "match": "Switzerland vs Bosnia and Herzegovina",
          "date": "2026-06-18",
          "stage": "Group B - Matchday 2",
          "actual": "4-1",
          "pred_home": 0.3719,
          "pred_draw": 0.3083,
          "pred_away": 0.3198,
          "brier": 0.59187,
          "direction": "correct"
        },
        {
          "match": "Canada vs Qatar",
          "date": "2026-06-18",
          "stage": "Group B - Matchday 2",
          "actual": "6-0",
          "pred_home": 0.3988,
          "pred_draw": 0.3063,
          "pred_away": 0.2949,
          "brier": 0.54219,
          "direction": "correct"
        },
        {
          "match": "Mexico vs South Korea",
          "date": "2026-06-19",
          "stage": "Group A - Matchday 2",
          "actual": "1-0",
          "pred_home": 0.5506,
          "pred_draw": 0.3715,
          "pred_away": 0.0779,
          "brier": 0.34604,
          "direction": "correct"
        },
        {
          "match": "United States vs Australia",
          "date": "2026-06-19",
          "stage": "Group D - Matchday 2",
          "actual": "2-0",
          "pred_home": 0.093,
          "pred_draw": 0.206,
          "pred_away": 0.7009,
          "brier": 1.35632,
          "direction": "wrong"
        },
        {
          "match": "Scotland vs Morocco",
          "date": "2026-06-19",
          "stage": "Group C - Matchday 2",
          "actual": "0-1",
          "pred_home": 0.1511,
          "pred_draw": 0.4952,
          "pred_away": 0.3537,
          "brier": 0.68584,
          "direction": "wrong"
        },
        {
          "match": "Brazil vs Haiti",
          "date": "2026-06-20",
          "stage": "Group C - Matchday 2",
          "actual": "3-0",
          "pred_home": 0.7466,
          "pred_draw": 0.2033,
          "pred_away": 0.0501,
          "brier": 0.10805,
          "direction": "correct"
        },
        {
          "match": "Turkey vs Paraguay",
          "date": "2026-06-20",
          "stage": "Group D - Matchday 2",
          "actual": "0-1",
          "pred_home": 0.3545,
          "pred_draw": 0.3387,
          "pred_away": 0.3068,
          "brier": 0.72082,
          "direction": "wrong"
        },
        {
          "match": "Netherlands vs Sweden",
          "date": "2026-06-20",
          "stage": "Group F - Matchday 2",
          "actual": "5-1",
          "pred_home": 0.2918,
          "pred_draw": 0.1933,
          "pred_away": 0.5149,
          "brier": 0.80409,
          "direction": "wrong"
        },
        {
          "match": "Germany vs Ivory Coast",
          "date": "2026-06-20",
          "stage": "Group E - Matchday 2",
          "actual": "2-1",
          "pred_home": 0.2576,
          "pred_draw": 0.2921,
          "pred_away": 0.4503,
          "brier": 0.83925,
          "direction": "wrong"
        },
        {
          "match": "Ecuador vs Curacao",
          "date": "2026-06-21",
          "stage": "Group E - Matchday 2",
          "actual": "0-0",
          "pred_home": 0.5861,
          "pred_draw": 0.2856,
          "pred_away": 0.1284,
          "brier": 0.87038,
          "direction": "wrong"
        },
        {
          "match": "Tunisia vs Japan",
          "date": "2026-06-21",
          "stage": "Group F - Matchday 2",
          "actual": "0-4",
          "pred_home": 0.0588,
          "pred_draw": 0.1887,
          "pred_away": 0.7525,
          "brier": 0.10035,
          "direction": "correct"
        },
        {
          "match": "Spain vs Saudi Arabia",
          "date": "2026-06-21",
          "stage": "Group H - Matchday 2",
          "actual": "4-0",
          "pred_home": 0.662,
          "pred_draw": 0.2773,
          "pred_away": 0.0607,
          "brier": 0.19478,
          "direction": "correct"
        },
        {
          "match": "Belgium vs Iran",
          "date": "2026-06-21",
          "stage": "Group G - Matchday 2",
          "actual": "2-1",
          "pred_home": 0.7117,
          "pred_draw": 0.1827,
          "pred_away": 0.1057,
          "brier": 0.12767,
          "direction": "correct"
        },
        {
          "match": "Uruguay vs Cape Verde",
          "date": "2026-06-21",
          "stage": "Group H - Matchday 2",
          "actual": "2-2",
          "pred_home": 0.1633,
          "pred_draw": 0.4781,
          "pred_away": 0.3587,
          "brier": 0.42772,
          "direction": "correct"
        },
        {
          "match": "New Zealand vs Egypt",
          "date": "2026-06-22",
          "stage": "Group G - Matchday 2",
          "actual": "1-3",
          "pred_home": 0.0996,
          "pred_draw": 0.2837,
          "pred_away": 0.6168,
          "brier": 0.23724,
          "direction": "correct"
        },
        {
          "match": "Argentina vs Austria",
          "date": "2026-06-22",
          "stage": "Group J - Matchday 2",
          "actual": "2-0",
          "pred_home": 0.6962,
          "pred_draw": 0.231,
          "pred_away": 0.0729,
          "brier": 0.15098,
          "direction": "correct"
        },
        {
          "match": "France vs Iraq",
          "date": "2026-06-22",
          "stage": "Group I - Matchday 2",
          "actual": "3-0",
          "pred_home": 0.9145,
          "pred_draw": 0.0701,
          "pred_away": 0.0154,
          "brier": 0.01246,
          "direction": "correct"
        },
        {
          "match": "Norway vs Senegal",
          "date": "2026-06-23",
          "stage": "Group I - Matchday 2",
          "actual": "3-2",
          "pred_home": 0.4017,
          "pred_draw": 0.2587,
          "pred_away": 0.3395,
          "brier": 0.54014,
          "direction": "correct"
        },
        {
          "match": "Jordan vs Algeria",
          "date": "2026-06-23",
          "stage": "Group J - Matchday 2",
          "actual": "1-2",
          "pred_home": 0.1316,
          "pred_draw": 0.2113,
          "pred_away": 0.6571,
          "brier": 0.17957,
          "direction": "correct"
        },
        {
          "match": "Portugal vs Uzbekistan",
          "date": "2026-06-23",
          "stage": "Group K - Matchday 2",
          "actual": "5-0",
          "pred_home": 0.9002,
          "pred_draw": 0.0832,
          "pred_away": 0.0167,
          "brier": 0.01716,
          "direction": "correct"
        },
        {
          "match": "England vs Ghana",
          "date": "2026-06-23",
          "stage": "Group L - Matchday 2",
          "actual": "0-0",
          "pred_home": 0.5977,
          "pred_draw": 0.2875,
          "pred_away": 0.1147,
          "brier": 0.87812,
          "direction": "wrong"
        },
        {
          "match": "Panama vs Croatia",
          "date": "2026-06-23",
          "stage": "Group L - Matchday 2",
          "actual": "0-1",
          "pred_home": 0.1277,
          "pred_draw": 0.223,
          "pred_away": 0.6494,
          "brier": 0.18897,
          "direction": "correct"
        },
        {
          "match": "Colombia vs DR Congo",
          "date": "2026-06-24",
          "stage": "Group K - Matchday 2",
          "actual": "1-0",
          "pred_home": 0.123,
          "pred_draw": 0.3159,
          "pred_away": 0.5611,
          "brier": 1.18376,
          "direction": "wrong"
        },
        {
          "match": "Switzerland vs Canada",
          "date": "2026-06-24",
          "stage": "Group B - Matchday 3",
          "actual": "2-1",
          "pred_home": 0.1805,
          "pred_draw": 0.3042,
          "pred_away": 0.5153,
          "brier": 1.02954,
          "direction": "wrong"
        },
        {
          "match": "Bosnia and Herzegovina vs Qatar",
          "date": "2026-06-24",
          "stage": "Group B - Matchday 3",
          "actual": "3-1",
          "pred_home": 0.6334,
          "pred_draw": 0.2756,
          "pred_away": 0.0909,
          "brier": 0.21863,
          "direction": "correct"
        },
        {
          "match": "Scotland vs Brazil",
          "date": "2026-06-24",
          "stage": "Group C - Matchday 3",
          "actual": "0-3",
          "pred_home": 0.155,
          "pred_draw": 0.3637,
          "pred_away": 0.4812,
          "brier": 0.42544,
          "direction": "correct"
        },
        {
          "match": "Morocco vs Haiti",
          "date": "2026-06-24",
          "stage": "Group C - Matchday 3",
          "actual": "4-2",
          "pred_home": 0.8044,
          "pred_draw": 0.1828,
          "pred_away": 0.0128,
          "brier": 0.07187,
          "direction": "correct"
        },
        {
          "match": "Czech Republic vs Mexico",
          "date": "2026-06-25",
          "stage": "Group A - Matchday 3",
          "actual": "0-3",
          "pred_home": 0.0308,
          "pred_draw": 0.177,
          "pred_away": 0.7923,
          "brier": 0.07541,
          "direction": "correct"
        },
        {
          "match": "South Africa vs South Korea",
          "date": "2026-06-25",
          "stage": "Group A - Matchday 3",
          "actual": "1-0",
          "pred_home": 0.1214,
          "pred_draw": 0.3335,
          "pred_away": 0.5451,
          "brier": 1.18031,
          "direction": "wrong"
        },
        {
          "match": "South Africa vs Canada",
          "date": "2026-06-28",
          "stage": "Round of 32",
          "actual": "0-1",
          "pred_home": 0.1078,
          "pred_draw": 0.2697,
          "pred_away": 0.6225,
          "brier": 0.22689,
          "direction": "correct"
        },
        {
          "match": "Netherlands vs Morocco",
          "date": "2026-06-29",
          "stage": "Round of 32",
          "actual": "1-1",
          "pred_home": 0.6515,
          "pred_draw": 0.2162,
          "pred_away": 0.1323,
          "brier": 1.05629,
          "direction": "wrong"
        },
        {
          "match": "Germany vs Paraguay",
          "date": "2026-06-29",
          "stage": "Round of 32",
          "actual": "1-1",
          "pred_home": 0.832,
          "pred_draw": 0.1195,
          "pred_away": 0.0485,
          "brier": 1.46985,
          "direction": "wrong"
        },
        {
          "match": "Brazil vs Japan",
          "date": "2026-06-29",
          "stage": "Round of 32 - 1st Group C vs 2nd Group F",
          "actual": "2-1",
          "pred_home": 0.2295,
          "pred_draw": 0.3519,
          "pred_away": 0.4186,
          "brier": 0.89274,
          "direction": "wrong"
        }
      ]
    },
    {
      "half_life_days": 90,
      "overall": {
        "brier_score": 0.5591099530693657,
        "log_loss": 0.9348373170135579,
        "direction_accuracy": 0.5689655172413793,
        "direction_counts": {
          "correct": 33,
          "wrong": 25
        }
      },
      "n_matches_evaluated": 58,
      "walk_forward_fits": 17,
      "fit_time_s": 829.7,
      "details": [
        {
          "match": "Mexico vs South Africa",
          "date": "2026-06-11",
          "stage": "Group A - Matchday 1",
          "actual": "2-0",
          "pred_home": 0.632,
          "pred_draw": 0.2778,
          "pred_away": 0.0902,
          "brier": 0.2207,
          "direction": "correct"
        },
        {
          "match": "South Korea vs Czech Republic",
          "date": "2026-06-12",
          "stage": "Group A - Matchday 1",
          "actual": "2-1",
          "pred_home": 0.4458,
          "pred_draw": 0.3743,
          "pred_away": 0.1799,
          "brier": 0.47952,
          "direction": "correct"
        },
        {
          "match": "Canada vs Bosnia and Herzegovina",
          "date": "2026-06-12",
          "stage": "Group B - Matchday 1",
          "actual": "1-1",
          "pred_home": 0.3229,
          "pred_draw": 0.4639,
          "pred_away": 0.2131,
          "brier": 0.43712,
          "direction": "correct"
        },
        {
          "match": "United States vs Paraguay",
          "date": "2026-06-13",
          "stage": "Group D - Matchday 1",
          "actual": "4-1",
          "pred_home": 0.2225,
          "pred_draw": 0.2757,
          "pred_away": 0.5017,
          "brier": 0.93222,
          "direction": "wrong"
        },
        {
          "match": "Australia vs Turkey",
          "date": "2026-06-13",
          "stage": "Group D - Matchday 1",
          "actual": "2-0",
          "pred_home": 0.2107,
          "pred_draw": 0.3766,
          "pred_away": 0.4127,
          "brier": 0.93507,
          "direction": "wrong"
        },
        {
          "match": "Qatar vs Switzerland",
          "date": "2026-06-13",
          "stage": "Group B - Matchday 1",
          "actual": "1-1",
          "pred_home": 0.0125,
          "pred_draw": 0.076,
          "pred_away": 0.9115,
          "brier": 1.68469,
          "direction": "wrong"
        },
        {
          "match": "Brazil vs Morocco",
          "date": "2026-06-13",
          "stage": "Group C - Matchday 1",
          "actual": "1-1",
          "pred_home": 0.1245,
          "pred_draw": 0.2484,
          "pred_away": 0.627,
          "brier": 0.97356,
          "direction": "wrong"
        },
        {
          "match": "Haiti vs Scotland",
          "date": "2026-06-14",
          "stage": "Group C - Matchday 1",
          "actual": "0-1",
          "pred_home": 0.1783,
          "pred_draw": 0.3117,
          "pred_away": 0.51,
          "brier": 0.36911,
          "direction": "correct"
        },
        {
          "match": "Germany vs Curacao",
          "date": "2026-06-14",
          "stage": "Group E - Matchday 1",
          "actual": "7-1",
          "pred_home": 0.8707,
          "pred_draw": 0.095,
          "pred_away": 0.0343,
          "brier": 0.02694,
          "direction": "correct"
        },
        {
          "match": "Netherlands vs Japan",
          "date": "2026-06-14",
          "stage": "Group F - Matchday 1",
          "actual": "2-2",
          "pred_home": 0.1433,
          "pred_draw": 0.4139,
          "pred_away": 0.4428,
          "brier": 0.56011,
          "direction": "wrong"
        },
        {
          "match": "Ivory Coast vs Ecuador",
          "date": "2026-06-14",
          "stage": "Group E - Matchday 1",
          "actual": "1-0",
          "pred_home": 0.281,
          "pred_draw": 0.4292,
          "pred_away": 0.2898,
          "brier": 0.78506,
          "direction": "wrong"
        },
        {
          "match": "Tunisia vs Sweden",
          "date": "2026-06-15",
          "stage": "Group F - Matchday 1",
          "actual": "1-5",
          "pred_home": 0.5729,
          "pred_draw": 0.2174,
          "pred_away": 0.2097,
          "brier": 0.99998,
          "direction": "wrong"
        },
        {
          "match": "Spain vs Cape Verde",
          "date": "2026-06-15",
          "stage": "Group H - Matchday 1",
          "actual": "0-0",
          "pred_home": 0.7225,
          "pred_draw": 0.1794,
          "pred_away": 0.0981,
          "brier": 1.20492,
          "direction": "wrong"
        },
        {
          "match": "Belgium vs Egypt",
          "date": "2026-06-15",
          "stage": "Group G - Matchday 1",
          "actual": "1-1",
          "pred_home": 0.4803,
          "pred_draw": 0.3171,
          "pred_away": 0.2026,
          "brier": 0.7381,
          "direction": "wrong"
        },
        {
          "match": "Saudi Arabia vs Uruguay",
          "date": "2026-06-15",
          "stage": "Group H - Matchday 1",
          "actual": "1-1",
          "pred_home": 0.1821,
          "pred_draw": 0.3386,
          "pred_away": 0.4793,
          "brier": 0.70035,
          "direction": "wrong"
        },
        {
          "match": "Iran vs New Zealand",
          "date": "2026-06-16",
          "stage": "Group G - Matchday 1",
          "actual": "2-2",
          "pred_home": 0.7006,
          "pred_draw": 0.2157,
          "pred_away": 0.0837,
          "brier": 1.11299,
          "direction": "wrong"
        },
        {
          "match": "France vs Senegal",
          "date": "2026-06-16",
          "stage": "Group I - Matchday 1",
          "actual": "3-1",
          "pred_home": 0.5164,
          "pred_draw": 0.2863,
          "pred_away": 0.1974,
          "brier": 0.35479,
          "direction": "correct"
        },
        {
          "match": "Iraq vs Norway",
          "date": "2026-06-16",
          "stage": "Group I - Matchday 1",
          "actual": "1-4",
          "pred_home": 0.1397,
          "pred_draw": 0.4013,
          "pred_away": 0.4591,
          "brier": 0.47309,
          "direction": "correct"
        },
        {
          "match": "Argentina vs Algeria",
          "date": "2026-06-17",
          "stage": "Group J - Matchday 1",
          "actual": "3-0",
          "pred_home": 0.335,
          "pred_draw": 0.3365,
          "pred_away": 0.3285,
          "brier": 0.66344,
          "direction": "wrong"
        },
        {
          "match": "Austria vs Jordan",
          "date": "2026-06-17",
          "stage": "Group J - Matchday 1",
          "actual": "3-1",
          "pred_home": 0.6691,
          "pred_draw": 0.2005,
          "pred_away": 0.1305,
          "brier": 0.16674,
          "direction": "correct"
        },
        {
          "match": "Portugal vs DR Congo",
          "date": "2026-06-17",
          "stage": "Group K - Matchday 1",
          "actual": "1-1",
          "pred_home": 0.3251,
          "pred_draw": 0.4244,
          "pred_away": 0.2505,
          "brier": 0.49974,
          "direction": "correct"
        },
        {
          "match": "England vs Croatia",
          "date": "2026-06-17",
          "stage": "Group L - Matchday 1",
          "actual": "4-2",
          "pred_home": 0.4273,
          "pred_draw": 0.3374,
          "pred_away": 0.2353,
          "brier": 0.49719,
          "direction": "correct"
        },
        {
          "match": "Ghana vs Panama",
          "date": "2026-06-17",
          "stage": "Group L - Matchday 1",
          "actual": "1-0",
          "pred_home": 0.3783,
          "pred_draw": 0.259,
          "pred_away": 0.3628,
          "brier": 0.58517,
          "direction": "correct"
        },
        {
          "match": "Uzbekistan vs Colombia",
          "date": "2026-06-18",
          "stage": "Group K - Matchday 1",
          "actual": "1-3",
          "pred_home": 0.2325,
          "pred_draw": 0.3598,
          "pred_away": 0.4077,
          "brier": 0.5343,
          "direction": "correct"
        },
        {
          "match": "Czech Republic vs South Africa",
          "date": "2026-06-18",
          "stage": "Group A - Matchday 2",
          "actual": "1-1",
          "pred_home": 0.4438,
          "pred_draw": 0.2703,
          "pred_away": 0.2859,
          "brier": 0.81113,
          "direction": "wrong"
        },
        {
          "match": "Switzerland vs Bosnia and Herzegovina",
          "date": "2026-06-18",
          "stage": "Group B - Matchday 2",
          "actual": "4-1",
          "pred_home": 0.6356,
          "pred_draw": 0.2535,
          "pred_away": 0.1109,
          "brier": 0.20937,
          "direction": "correct"
        },
        {
          "match": "Canada vs Qatar",
          "date": "2026-06-18",
          "stage": "Group B - Matchday 2",
          "actual": "6-0",
          "pred_home": 0.4589,
          "pred_draw": 0.3643,
          "pred_away": 0.1768,
          "brier": 0.45683,
          "direction": "correct"
        },
        {
          "match": "Mexico vs South Korea",
          "date": "2026-06-19",
          "stage": "Group A - Matchday 2",
          "actual": "1-0",
          "pred_home": 0.5166,
          "pred_draw": 0.3245,
          "pred_away": 0.159,
          "brier": 0.36427,
          "direction": "correct"
        },
        {
          "match": "United States vs Australia",
          "date": "2026-06-19",
          "stage": "Group D - Matchday 2",
          "actual": "2-0",
          "pred_home": 0.157,
          "pred_draw": 0.2026,
          "pred_away": 0.6404,
          "brier": 1.16189,
          "direction": "wrong"
        },
        {
          "match": "Scotland vs Morocco",
          "date": "2026-06-19",
          "stage": "Group C - Matchday 2",
          "actual": "0-1",
          "pred_home": 0.2009,
          "pred_draw": 0.3626,
          "pred_away": 0.4365,
          "brier": 0.48934,
          "direction": "correct"
        },
        {
          "match": "Brazil vs Haiti",
          "date": "2026-06-20",
          "stage": "Group C - Matchday 2",
          "actual": "3-0",
          "pred_home": 0.8319,
          "pred_draw": 0.1331,
          "pred_away": 0.035,
          "brier": 0.04719,
          "direction": "correct"
        },
        {
          "match": "Turkey vs Paraguay",
          "date": "2026-06-20",
          "stage": "Group D - Matchday 2",
          "actual": "0-1",
          "pred_home": 0.4077,
          "pred_draw": 0.311,
          "pred_away": 0.2813,
          "brier": 0.77946,
          "direction": "wrong"
        },
        {
          "match": "Netherlands vs Sweden",
          "date": "2026-06-20",
          "stage": "Group F - Matchday 2",
          "actual": "5-1",
          "pred_home": 0.3471,
          "pred_draw": 0.2112,
          "pred_away": 0.4416,
          "brier": 0.66587,
          "direction": "wrong"
        },
        {
          "match": "Germany vs Ivory Coast",
          "date": "2026-06-20",
          "stage": "Group E - Matchday 2",
          "actual": "2-1",
          "pred_home": 0.2467,
          "pred_draw": 0.3276,
          "pred_away": 0.4257,
          "brier": 0.85604,
          "direction": "wrong"
        },
        {
          "match": "Ecuador vs Curacao",
          "date": "2026-06-21",
          "stage": "Group E - Matchday 2",
          "actual": "0-0",
          "pred_home": 0.5492,
          "pred_draw": 0.3373,
          "pred_away": 0.1135,
          "brier": 0.75358,
          "direction": "wrong"
        },
        {
          "match": "Tunisia vs Japan",
          "date": "2026-06-21",
          "stage": "Group F - Matchday 2",
          "actual": "0-4",
          "pred_home": 0.0673,
          "pred_draw": 0.239,
          "pred_away": 0.6938,
          "brier": 0.1554,
          "direction": "correct"
        },
        {
          "match": "Spain vs Saudi Arabia",
          "date": "2026-06-21",
          "stage": "Group H - Matchday 2",
          "actual": "4-0",
          "pred_home": 0.8313,
          "pred_draw": 0.1432,
          "pred_away": 0.0255,
          "brier": 0.04962,
          "direction": "correct"
        },
        {
          "match": "Belgium vs Iran",
          "date": "2026-06-21",
          "stage": "Group G - Matchday 2",
          "actual": "2-1",
          "pred_home": 0.7314,
          "pred_draw": 0.1795,
          "pred_away": 0.0891,
          "brier": 0.11226,
          "direction": "correct"
        },
        {
          "match": "Uruguay vs Cape Verde",
          "date": "2026-06-21",
          "stage": "Group H - Matchday 2",
          "actual": "2-2",
          "pred_home": 0.1413,
          "pred_draw": 0.4944,
          "pred_away": 0.3643,
          "brier": 0.40836,
          "direction": "correct"
        },
        {
          "match": "New Zealand vs Egypt",
          "date": "2026-06-22",
          "stage": "Group G - Matchday 2",
          "actual": "1-3",
          "pred_home": 0.1261,
          "pred_draw": 0.3077,
          "pred_away": 0.5662,
          "brier": 0.29877,
          "direction": "correct"
        },
        {
          "match": "Argentina vs Austria",
          "date": "2026-06-22",
          "stage": "Group J - Matchday 2",
          "actual": "2-0",
          "pred_home": 0.6218,
          "pred_draw": 0.2814,
          "pred_away": 0.0968,
          "brier": 0.23156,
          "direction": "correct"
        },
        {
          "match": "France vs Iraq",
          "date": "2026-06-22",
          "stage": "Group I - Matchday 2",
          "actual": "3-0",
          "pred_home": 0.8613,
          "pred_draw": 0.1121,
          "pred_away": 0.0265,
          "brier": 0.0325,
          "direction": "correct"
        },
        {
          "match": "Norway vs Senegal",
          "date": "2026-06-23",
          "stage": "Group I - Matchday 2",
          "actual": "3-2",
          "pred_home": 0.5405,
          "pred_draw": 0.2139,
          "pred_away": 0.2456,
          "brier": 0.3172,
          "direction": "correct"
        },
        {
          "match": "Jordan vs Algeria",
          "date": "2026-06-23",
          "stage": "Group J - Matchday 2",
          "actual": "1-2",
          "pred_home": 0.1867,
          "pred_draw": 0.1938,
          "pred_away": 0.6196,
          "brier": 0.21711,
          "direction": "correct"
        },
        {
          "match": "Portugal vs Uzbekistan",
          "date": "2026-06-23",
          "stage": "Group K - Matchday 2",
          "actual": "5-0",
          "pred_home": 0.7904,
          "pred_draw": 0.1444,
          "pred_away": 0.0652,
          "brier": 0.06906,
          "direction": "correct"
        },
        {
          "match": "England vs Ghana",
          "date": "2026-06-23",
          "stage": "Group L - Matchday 2",
          "actual": "0-0",
          "pred_home": 0.5759,
          "pred_draw": 0.2466,
          "pred_away": 0.1775,
          "brier": 0.93074,
          "direction": "wrong"
        },
        {
          "match": "Panama vs Croatia",
          "date": "2026-06-23",
          "stage": "Group L - Matchday 2",
          "actual": "0-1",
          "pred_home": 0.2323,
          "pred_draw": 0.2207,
          "pred_away": 0.547,
          "brier": 0.30782,
          "direction": "correct"
        },
        {
          "match": "Colombia vs DR Congo",
          "date": "2026-06-24",
          "stage": "Group K - Matchday 2",
          "actual": "1-0",
          "pred_home": 0.1264,
          "pred_draw": 0.3255,
          "pred_away": 0.5482,
          "brier": 1.16968,
          "direction": "wrong"
        },
        {
          "match": "Switzerland vs Canada",
          "date": "2026-06-24",
          "stage": "Group B - Matchday 3",
          "actual": "2-1",
          "pred_home": 0.2368,
          "pred_draw": 0.3345,
          "pred_away": 0.4287,
          "brier": 0.8782,
          "direction": "wrong"
        },
        {
          "match": "Bosnia and Herzegovina vs Qatar",
          "date": "2026-06-24",
          "stage": "Group B - Matchday 3",
          "actual": "3-1",
          "pred_home": 0.7759,
          "pred_draw": 0.1775,
          "pred_away": 0.0466,
          "brier": 0.08391,
          "direction": "correct"
        },
        {
          "match": "Scotland vs Brazil",
          "date": "2026-06-24",
          "stage": "Group C - Matchday 3",
          "actual": "0-3",
          "pred_home": 0.1399,
          "pred_draw": 0.2973,
          "pred_away": 0.5628,
          "brier": 0.29915,
          "direction": "correct"
        },
        {
          "match": "Morocco vs Haiti",
          "date": "2026-06-24",
          "stage": "Group C - Matchday 3",
          "actual": "4-2",
          "pred_home": 0.7616,
          "pred_draw": 0.2232,
          "pred_away": 0.0152,
          "brier": 0.10691,
          "direction": "correct"
        },
        {
          "match": "Czech Republic vs Mexico",
          "date": "2026-06-25",
          "stage": "Group A - Matchday 3",
          "actual": "0-3",
          "pred_home": 0.0522,
          "pred_draw": 0.2338,
          "pred_away": 0.7141,
          "brier": 0.13915,
          "direction": "correct"
        },
        {
          "match": "South Africa vs South Korea",
          "date": "2026-06-25",
          "stage": "Group A - Matchday 3",
          "actual": "1-0",
          "pred_home": 0.1597,
          "pred_draw": 0.2873,
          "pred_away": 0.5531,
          "brier": 1.09457,
          "direction": "wrong"
        },
        {
          "match": "South Africa vs Canada",
          "date": "2026-06-28",
          "stage": "Round of 32",
          "actual": "0-1",
          "pred_home": 0.1806,
          "pred_draw": 0.2687,
          "pred_away": 0.5508,
          "brier": 0.3066,
          "direction": "correct"
        },
        {
          "match": "Netherlands vs Morocco",
          "date": "2026-06-29",
          "stage": "Round of 32",
          "actual": "1-1",
          "pred_home": 0.3647,
          "pred_draw": 0.2918,
          "pred_away": 0.3434,
          "brier": 0.75248,
          "direction": "wrong"
        },
        {
          "match": "Germany vs Paraguay",
          "date": "2026-06-29",
          "stage": "Round of 32",
          "actual": "1-1",
          "pred_home": 0.5805,
          "pred_draw": 0.2395,
          "pred_away": 0.18,
          "brier": 0.94779,
          "direction": "wrong"
        },
        {
          "match": "Brazil vs Japan",
          "date": "2026-06-29",
          "stage": "Round of 32 - 1st Group C vs 2nd Group F",
          "actual": "2-1",
          "pred_home": 0.1967,
          "pred_draw": 0.2973,
          "pred_away": 0.506,
          "brier": 0.98966,
          "direction": "wrong"
        }
      ]
    },
    {
      "half_life_days": 180,
      "overall": {
        "brier_score": 0.5410733216755669,
        "log_loss": 0.9023999777676152,
        "direction_accuracy": 0.5689655172413793,
        "direction_counts": {
          "correct": 33,
          "wrong": 25
        }
      },
      "n_matches_evaluated": 58,
      "walk_forward_fits": 17,
      "fit_time_s": 908.1,
      "details": [
        {
          "match": "Mexico vs South Africa",
          "date": "2026-06-11",
          "stage": "Group A - Matchday 1",
          "actual": "2-0",
          "pred_home": 0.5214,
          "pred_draw": 0.3403,
          "pred_away": 0.1383,
          "brier": 0.364,
          "direction": "correct"
        },
        {
          "match": "South Korea vs Czech Republic",
          "date": "2026-06-12",
          "stage": "Group A - Matchday 1",
          "actual": "2-1",
          "pred_home": 0.5613,
          "pred_draw": 0.2743,
          "pred_away": 0.1644,
          "brier": 0.29473,
          "direction": "correct"
        },
        {
          "match": "Canada vs Bosnia and Herzegovina",
          "date": "2026-06-12",
          "stage": "Group B - Matchday 1",
          "actual": "1-1",
          "pred_home": 0.5131,
          "pred_draw": 0.3545,
          "pred_away": 0.1324,
          "brier": 0.69746,
          "direction": "wrong"
        },
        {
          "match": "United States vs Paraguay",
          "date": "2026-06-13",
          "stage": "Group D - Matchday 1",
          "actual": "4-1",
          "pred_home": 0.1883,
          "pred_draw": 0.295,
          "pred_away": 0.5167,
          "brier": 1.0128,
          "direction": "wrong"
        },
        {
          "match": "Australia vs Turkey",
          "date": "2026-06-13",
          "stage": "Group D - Matchday 1",
          "actual": "2-0",
          "pred_home": 0.3302,
          "pred_draw": 0.3624,
          "pred_away": 0.3074,
          "brier": 0.67437,
          "direction": "wrong"
        },
        {
          "match": "Qatar vs Switzerland",
          "date": "2026-06-13",
          "stage": "Group B - Matchday 1",
          "actual": "1-1",
          "pred_home": 0.0367,
          "pred_draw": 0.1187,
          "pred_away": 0.8446,
          "brier": 1.49131,
          "direction": "wrong"
        },
        {
          "match": "Brazil vs Morocco",
          "date": "2026-06-13",
          "stage": "Group C - Matchday 1",
          "actual": "1-1",
          "pred_home": 0.215,
          "pred_draw": 0.3664,
          "pred_away": 0.4186,
          "brier": 0.6229,
          "direction": "wrong"
        },
        {
          "match": "Haiti vs Scotland",
          "date": "2026-06-14",
          "stage": "Group C - Matchday 1",
          "actual": "0-1",
          "pred_home": 0.2976,
          "pred_draw": 0.2771,
          "pred_away": 0.4252,
          "brier": 0.49577,
          "direction": "correct"
        },
        {
          "match": "Germany vs Curacao",
          "date": "2026-06-14",
          "stage": "Group E - Matchday 1",
          "actual": "7-1",
          "pred_home": 0.7393,
          "pred_draw": 0.1602,
          "pred_away": 0.1005,
          "brier": 0.10373,
          "direction": "correct"
        },
        {
          "match": "Netherlands vs Japan",
          "date": "2026-06-14",
          "stage": "Group F - Matchday 1",
          "actual": "2-2",
          "pred_home": 0.2002,
          "pred_draw": 0.3148,
          "pred_away": 0.485,
          "brier": 0.74479,
          "direction": "wrong"
        },
        {
          "match": "Ivory Coast vs Ecuador",
          "date": "2026-06-14",
          "stage": "Group E - Matchday 1",
          "actual": "1-0",
          "pred_home": 0.2303,
          "pred_draw": 0.4594,
          "pred_away": 0.3103,
          "brier": 0.89976,
          "direction": "wrong"
        },
        {
          "match": "Tunisia vs Sweden",
          "date": "2026-06-15",
          "stage": "Group F - Matchday 1",
          "actual": "1-5",
          "pred_home": 0.4316,
          "pred_draw": 0.3037,
          "pred_away": 0.2647,
          "brier": 0.81922,
          "direction": "wrong"
        },
        {
          "match": "Spain vs Cape Verde",
          "date": "2026-06-15",
          "stage": "Group H - Matchday 1",
          "actual": "0-0",
          "pred_home": 0.7337,
          "pred_draw": 0.1922,
          "pred_away": 0.0741,
          "brier": 1.19644,
          "direction": "wrong"
        },
        {
          "match": "Belgium vs Egypt",
          "date": "2026-06-15",
          "stage": "Group G - Matchday 1",
          "actual": "1-1",
          "pred_home": 0.3735,
          "pred_draw": 0.3779,
          "pred_away": 0.2487,
          "brier": 0.58833,
          "direction": "correct"
        },
        {
          "match": "Saudi Arabia vs Uruguay",
          "date": "2026-06-15",
          "stage": "Group H - Matchday 1",
          "actual": "1-1",
          "pred_home": 0.1365,
          "pred_draw": 0.385,
          "pred_away": 0.4785,
          "brier": 0.62575,
          "direction": "wrong"
        },
        {
          "match": "Iran vs New Zealand",
          "date": "2026-06-16",
          "stage": "Group G - Matchday 1",
          "actual": "2-2",
          "pred_home": 0.3919,
          "pred_draw": 0.3575,
          "pred_away": 0.2506,
          "brier": 0.62919,
          "direction": "wrong"
        },
        {
          "match": "France vs Senegal",
          "date": "2026-06-16",
          "stage": "Group I - Matchday 1",
          "actual": "3-1",
          "pred_home": 0.4474,
          "pred_draw": 0.3176,
          "pred_away": 0.235,
          "brier": 0.46145,
          "direction": "correct"
        },
        {
          "match": "Iraq vs Norway",
          "date": "2026-06-16",
          "stage": "Group I - Matchday 1",
          "actual": "1-4",
          "pred_home": 0.125,
          "pred_draw": 0.3222,
          "pred_away": 0.5528,
          "brier": 0.31942,
          "direction": "correct"
        },
        {
          "match": "Argentina vs Algeria",
          "date": "2026-06-17",
          "stage": "Group J - Matchday 1",
          "actual": "3-0",
          "pred_home": 0.5417,
          "pred_draw": 0.3417,
          "pred_away": 0.1166,
          "brier": 0.34037,
          "direction": "correct"
        },
        {
          "match": "Austria vs Jordan",
          "date": "2026-06-17",
          "stage": "Group J - Matchday 1",
          "actual": "3-1",
          "pred_home": 0.5389,
          "pred_draw": 0.2814,
          "pred_away": 0.1798,
          "brier": 0.32411,
          "direction": "correct"
        },
        {
          "match": "Portugal vs DR Congo",
          "date": "2026-06-17",
          "stage": "Group K - Matchday 1",
          "actual": "1-1",
          "pred_home": 0.4362,
          "pred_draw": 0.3827,
          "pred_away": 0.1811,
          "brier": 0.60403,
          "direction": "wrong"
        },
        {
          "match": "England vs Croatia",
          "date": "2026-06-17",
          "stage": "Group L - Matchday 1",
          "actual": "4-2",
          "pred_home": 0.4862,
          "pred_draw": 0.3497,
          "pred_away": 0.1641,
          "brier": 0.41317,
          "direction": "correct"
        },
        {
          "match": "Ghana vs Panama",
          "date": "2026-06-17",
          "stage": "Group L - Matchday 1",
          "actual": "1-0",
          "pred_home": 0.3058,
          "pred_draw": 0.3242,
          "pred_away": 0.37,
          "brier": 0.724,
          "direction": "wrong"
        },
        {
          "match": "Uzbekistan vs Colombia",
          "date": "2026-06-18",
          "stage": "Group K - Matchday 1",
          "actual": "1-3",
          "pred_home": 0.2002,
          "pred_draw": 0.3629,
          "pred_away": 0.4369,
          "brier": 0.48883,
          "direction": "correct"
        },
        {
          "match": "Czech Republic vs South Africa",
          "date": "2026-06-18",
          "stage": "Group A - Matchday 2",
          "actual": "1-1",
          "pred_home": 0.4015,
          "pred_draw": 0.3092,
          "pred_away": 0.2893,
          "brier": 0.72205,
          "direction": "wrong"
        },
        {
          "match": "Switzerland vs Bosnia and Herzegovina",
          "date": "2026-06-18",
          "stage": "Group B - Matchday 2",
          "actual": "4-1",
          "pred_home": 0.5663,
          "pred_draw": 0.2935,
          "pred_away": 0.1402,
          "brier": 0.29395,
          "direction": "correct"
        },
        {
          "match": "Canada vs Qatar",
          "date": "2026-06-18",
          "stage": "Group B - Matchday 2",
          "actual": "6-0",
          "pred_home": 0.5577,
          "pred_draw": 0.3133,
          "pred_away": 0.129,
          "brier": 0.31037,
          "direction": "correct"
        },
        {
          "match": "Mexico vs South Korea",
          "date": "2026-06-19",
          "stage": "Group A - Matchday 2",
          "actual": "1-0",
          "pred_home": 0.4253,
          "pred_draw": 0.3917,
          "pred_away": 0.183,
          "brier": 0.51725,
          "direction": "correct"
        },
        {
          "match": "United States vs Australia",
          "date": "2026-06-19",
          "stage": "Group D - Matchday 2",
          "actual": "2-0",
          "pred_home": 0.1829,
          "pred_draw": 0.309,
          "pred_away": 0.5081,
          "brier": 1.02123,
          "direction": "wrong"
        },
        {
          "match": "Scotland vs Morocco",
          "date": "2026-06-19",
          "stage": "Group C - Matchday 2",
          "actual": "0-1",
          "pred_home": 0.139,
          "pred_draw": 0.3805,
          "pred_away": 0.4805,
          "brier": 0.43393,
          "direction": "correct"
        },
        {
          "match": "Brazil vs Haiti",
          "date": "2026-06-20",
          "stage": "Group C - Matchday 2",
          "actual": "3-0",
          "pred_home": 0.675,
          "pred_draw": 0.228,
          "pred_away": 0.097,
          "brier": 0.16703,
          "direction": "correct"
        },
        {
          "match": "Turkey vs Paraguay",
          "date": "2026-06-20",
          "stage": "Group D - Matchday 2",
          "actual": "0-1",
          "pred_home": 0.3851,
          "pred_draw": 0.3239,
          "pred_away": 0.291,
          "brier": 0.75585,
          "direction": "wrong"
        },
        {
          "match": "Netherlands vs Sweden",
          "date": "2026-06-20",
          "stage": "Group F - Matchday 2",
          "actual": "5-1",
          "pred_home": 0.5211,
          "pred_draw": 0.2204,
          "pred_away": 0.2586,
          "brier": 0.34482,
          "direction": "correct"
        },
        {
          "match": "Germany vs Ivory Coast",
          "date": "2026-06-20",
          "stage": "Group E - Matchday 2",
          "actual": "2-1",
          "pred_home": 0.4599,
          "pred_draw": 0.3046,
          "pred_away": 0.2356,
          "brier": 0.43995,
          "direction": "correct"
        },
        {
          "match": "Ecuador vs Curacao",
          "date": "2026-06-21",
          "stage": "Group E - Matchday 2",
          "actual": "0-0",
          "pred_home": 0.6999,
          "pred_draw": 0.2423,
          "pred_away": 0.0577,
          "brier": 1.06726,
          "direction": "wrong"
        },
        {
          "match": "Tunisia vs Japan",
          "date": "2026-06-21",
          "stage": "Group F - Matchday 2",
          "actual": "0-4",
          "pred_home": 0.0763,
          "pred_draw": 0.2371,
          "pred_away": 0.6866,
          "brier": 0.16024,
          "direction": "correct"
        },
        {
          "match": "Spain vs Saudi Arabia",
          "date": "2026-06-21",
          "stage": "Group H - Matchday 2",
          "actual": "4-0",
          "pred_home": 0.7362,
          "pred_draw": 0.2088,
          "pred_away": 0.0549,
          "brier": 0.11621,
          "direction": "correct"
        },
        {
          "match": "Belgium vs Iran",
          "date": "2026-06-21",
          "stage": "Group G - Matchday 2",
          "actual": "2-1",
          "pred_home": 0.5175,
          "pred_draw": 0.2717,
          "pred_away": 0.2108,
          "brier": 0.35107,
          "direction": "correct"
        },
        {
          "match": "Uruguay vs Cape Verde",
          "date": "2026-06-21",
          "stage": "Group H - Matchday 2",
          "actual": "2-2",
          "pred_home": 0.33,
          "pred_draw": 0.4436,
          "pred_away": 0.2265,
          "brier": 0.46981,
          "direction": "correct"
        },
        {
          "match": "New Zealand vs Egypt",
          "date": "2026-06-22",
          "stage": "Group G - Matchday 2",
          "actual": "1-3",
          "pred_home": 0.2627,
          "pred_draw": 0.3963,
          "pred_away": 0.3409,
          "brier": 0.66047,
          "direction": "wrong"
        },
        {
          "match": "Argentina vs Austria",
          "date": "2026-06-22",
          "stage": "Group J - Matchday 2",
          "actual": "2-0",
          "pred_home": 0.6079,
          "pred_draw": 0.3126,
          "pred_away": 0.0795,
          "brier": 0.25775,
          "direction": "correct"
        },
        {
          "match": "France vs Iraq",
          "date": "2026-06-22",
          "stage": "Group I - Matchday 2",
          "actual": "3-0",
          "pred_home": 0.8095,
          "pred_draw": 0.1571,
          "pred_away": 0.0334,
          "brier": 0.06209,
          "direction": "correct"
        },
        {
          "match": "Norway vs Senegal",
          "date": "2026-06-23",
          "stage": "Group I - Matchday 2",
          "actual": "3-2",
          "pred_home": 0.5193,
          "pred_draw": 0.2617,
          "pred_away": 0.219,
          "brier": 0.34745,
          "direction": "correct"
        },
        {
          "match": "Jordan vs Algeria",
          "date": "2026-06-23",
          "stage": "Group J - Matchday 2",
          "actual": "1-2",
          "pred_home": 0.2096,
          "pred_draw": 0.2576,
          "pred_away": 0.5328,
          "brier": 0.32851,
          "direction": "correct"
        },
        {
          "match": "Portugal vs Uzbekistan",
          "date": "2026-06-23",
          "stage": "Group K - Matchday 2",
          "actual": "5-0",
          "pred_home": 0.6571,
          "pred_draw": 0.2458,
          "pred_away": 0.0971,
          "brier": 0.18743,
          "direction": "correct"
        },
        {
          "match": "England vs Ghana",
          "date": "2026-06-23",
          "stage": "Group L - Matchday 2",
          "actual": "0-0",
          "pred_home": 0.5728,
          "pred_draw": 0.2886,
          "pred_away": 0.1386,
          "brier": 0.85332,
          "direction": "wrong"
        },
        {
          "match": "Panama vs Croatia",
          "date": "2026-06-23",
          "stage": "Group L - Matchday 2",
          "actual": "0-1",
          "pred_home": 0.231,
          "pred_draw": 0.2829,
          "pred_away": 0.4861,
          "brier": 0.39748,
          "direction": "correct"
        },
        {
          "match": "Colombia vs DR Congo",
          "date": "2026-06-24",
          "stage": "Group K - Matchday 2",
          "actual": "1-0",
          "pred_home": 0.3585,
          "pred_draw": 0.394,
          "pred_away": 0.2474,
          "brier": 0.62796,
          "direction": "wrong"
        },
        {
          "match": "Switzerland vs Canada",
          "date": "2026-06-24",
          "stage": "Group B - Matchday 3",
          "actual": "2-1",
          "pred_home": 0.3045,
          "pred_draw": 0.3603,
          "pred_away": 0.3352,
          "brier": 0.72584,
          "direction": "wrong"
        },
        {
          "match": "Bosnia and Herzegovina vs Qatar",
          "date": "2026-06-24",
          "stage": "Group B - Matchday 3",
          "actual": "3-1",
          "pred_home": 0.6174,
          "pred_draw": 0.2221,
          "pred_away": 0.1605,
          "brier": 0.22144,
          "direction": "correct"
        },
        {
          "match": "Scotland vs Brazil",
          "date": "2026-06-24",
          "stage": "Group C - Matchday 3",
          "actual": "0-3",
          "pred_home": 0.1761,
          "pred_draw": 0.2868,
          "pred_away": 0.5371,
          "brier": 0.32757,
          "direction": "correct"
        },
        {
          "match": "Morocco vs Haiti",
          "date": "2026-06-24",
          "stage": "Group C - Matchday 3",
          "actual": "4-2",
          "pred_home": 0.6649,
          "pred_draw": 0.2573,
          "pred_away": 0.0778,
          "brier": 0.18454,
          "direction": "correct"
        },
        {
          "match": "Czech Republic vs Mexico",
          "date": "2026-06-25",
          "stage": "Group A - Matchday 3",
          "actual": "0-3",
          "pred_home": 0.094,
          "pred_draw": 0.286,
          "pred_away": 0.62,
          "brier": 0.23497,
          "direction": "correct"
        },
        {
          "match": "South Africa vs South Korea",
          "date": "2026-06-25",
          "stage": "Group A - Matchday 3",
          "actual": "1-0",
          "pred_home": 0.1789,
          "pred_draw": 0.2877,
          "pred_away": 0.5334,
          "brier": 1.04148,
          "direction": "wrong"
        },
        {
          "match": "South Africa vs Canada",
          "date": "2026-06-28",
          "stage": "Round of 32",
          "actual": "0-1",
          "pred_home": 0.1529,
          "pred_draw": 0.301,
          "pred_away": 0.5461,
          "brier": 0.31999,
          "direction": "correct"
        },
        {
          "match": "Netherlands vs Morocco",
          "date": "2026-06-29",
          "stage": "Round of 32",
          "actual": "1-1",
          "pred_home": 0.3571,
          "pred_draw": 0.3176,
          "pred_away": 0.3253,
          "brier": 0.69892,
          "direction": "wrong"
        },
        {
          "match": "Germany vs Paraguay",
          "date": "2026-06-29",
          "stage": "Round of 32",
          "actual": "1-1",
          "pred_home": 0.6461,
          "pred_draw": 0.2184,
          "pred_away": 0.1355,
          "brier": 1.04676,
          "direction": "wrong"
        },
        {
          "match": "Brazil vs Japan",
          "date": "2026-06-29",
          "stage": "Round of 32 - 1st Group C vs 2nd Group F",
          "actual": "2-1",
          "pred_home": 0.2925,
          "pred_draw": 0.338,
          "pred_away": 0.3695,
          "brier": 0.75131,
          "direction": "wrong"
        }
      ]
    }
  ]
}